MANIFEST.in
README.rst
setup.py
jsonf/__init__.py
jsonf/cli.py
jsonf.egg-info/PKG-INFO
jsonf.egg-info/SOURCES.txt
jsonf.egg-info/dependency_links.txt
jsonf.egg-info/entry_points.txt
jsonf.egg-info/requires.txt
jsonf.egg-info/top_level.txt