Metadata-Version: 1.0
Name: jsonf
Version: 1.0
Summary: Tiny tool to pretty print JSON documents on the console.
Home-page: UNKNOWN
Author: Michel Albert
Author-email: michel@albert.lu
License: BSD
Platform: UNKNOWN
